py3rijndael/__init__.py
py3rijndael/constants.py
py3rijndael/paddings.py
py3rijndael/rijndael.py
py3rijndael/tests/__init__.py
py3rijndael/tests/test_padding.py
py3rijndael/tests/test_rijndael.py
py3rijndael/tests/test_rijndael_cbc.py
py3rijndael-0.3.3.dist-info/LICENSE
py3rijndael-0.3.3.dist-info/METADATA
py3rijndael-0.3.3.dist-info/WHEEL
py3rijndael-0.3.3.dist-info/top_level.txt
py3rijndael-0.3.3.dist-info/RECORD
