Metadata-Version: 2.1
Name: py3rijndael
Version: 0.3.3
Summary: Rijndael algorithm library for Python3.
Home-page: https://github.com/meyt/py3rijndael
Author: Mahdi Ghanea.g
Author-email: UNKNOWN
License: MIT License
Platform: UNKNOWN
Classifier: Environment :: Console
Classifier: Topic :: Security :: Cryptography
Classifier: Intended Audience :: Developers
Classifier: Natural Language :: English
Classifier: Development Status :: 3 - Alpha
Classifier: License :: OSI Approved :: MIT License
Classifier: Operating System :: OS Independent
Classifier: Programming Language :: Python :: 3.4
Classifier: Programming Language :: Python :: 3.5
Classifier: Programming Language :: Python :: 3.6
Classifier: Programming Language :: Python :: 3.7
Classifier: Topic :: Software Development
Classifier: Topic :: Software Development :: Libraries
Classifier: Topic :: Software Development :: Libraries :: Python Modules
